dashboard/__init__.py
dashboard/admin.py
dashboard/apps.py
dashboard/models.py
dashboard/tests.py
dashboard/views.py
dashboard/migrations/__init__.py
dashboard/templates/admin/dashboard.html
dashboard/templates/admin/icon_app_list.html
dashboard/templates/admin/icon_nav_sidebar.html
dashboard/templates/admin/modules/default.html
django_admin_index_modules/__init__.py
django_admin_index_modules/admin.py
django_admin_index_modules/apps.py
django_admin_index_modules/models.py
django_admin_index_modules/tests.py
django_admin_index_modules/views.py
django_admin_index_modules/migrations/__init__.py
django_admin_index_modules/static/django_admin_index_modules/admin/css/bootstarp-grid.css
django_admin_index_modules/templates/admin/dashboard.html
django_admin_index_modules/templates/admin/icon_app_list.html
django_admin_index_modules/templates/admin/icon_nav_sidebar.html
django_admin_index_modules/templates/admin/modules/default.html
modules_dashboard/__init__.py
modules_dashboard/admin.py
modules_dashboard/apps.py
modules_dashboard/models.py
modules_dashboard/tests.py
modules_dashboard/views.py
modules_dashboard/migrations/__init__.py
django_admin_index_modules-1.0.3.dist-info/LICENSE
django_admin_index_modules-1.0.3.dist-info/METADATA
django_admin_index_modules-1.0.3.dist-info/WHEEL
django_admin_index_modules-1.0.3.dist-info/top_level.txt
django_admin_index_modules-1.0.3.dist-info/RECORD
