Metadata-Version: 2.1
Name: django-admin-index-modules
Version: 1.0.3
Summary: Django admin index modules is a Django app that gives you the ability to add widgets modules to the django admin dashboard (admin index)
Home-page: https://github.com/Fethienv/django_admin_index_modules
Author: Fethi BEN ABDELHAMID
Author-email: fethi.env@gmail.com
Maintainer: Fethi BEN ABDELHAMID
Maintainer-email: fethi.env@gmail.com
License: MIT
Keywords: django admin index widgets modules
Platform: UNKNOWN
Classifier: Environment :: Web Environment
Classifier: Framework :: Django
Classifier: Intended Audience :: Developers
Classifier: License :: OSI Approved :: MIT License
Classifier: Operating System :: OS Independent
Classifier: Programming Language :: Python
Classifier: Programming Language :: Python :: 3
Classifier: Programming Language :: Python :: 3 :: Only
Classifier: Programming Language :: Python :: 3.8
Classifier: Programming Language :: Python :: 3.9
Classifier: Programming Language :: Python :: 3.10
Classifier: Topic :: Software Development :: Libraries :: Python Modules
Classifier: Topic :: Internet :: WWW/HTTP :: Dynamic Content
Requires-Python: >=3.8
Requires-Dist: Django (>=3.2)
